jafrdow/__init__.py
jafrdow/cli.py
jafrdow/core.py
jafrdow/exceptions.py
jafrdow-0.1.0.dist-info/licenses/LICENSE
jafrdow-0.1.0.dist-info/METADATA
jafrdow-0.1.0.dist-info/WHEEL
jafrdow-0.1.0.dist-info/entry_points.txt
jafrdow-0.1.0.dist-info/top_level.txt
jafrdow-0.1.0.dist-info/RECORD
